wagtail_audit_trail/__init__.py
wagtail_audit_trail/admin.py
wagtail_audit_trail/apps.py
wagtail_audit_trail/diff.py
wagtail_audit_trail/models.py
wagtail_audit_trail/signal_handlers.py
wagtail_audit_trail/utils.py
wagtail_audit_trail/views.py
wagtail_audit_trail/wagtail_hooks.py
wagtail_audit_trail/migrations/0001_initial.py
wagtail_audit_trail/migrations/0002_pagerecord_page_url.py
wagtail_audit_trail/migrations/__init__.py
wagtail_audit_trail/templates/wagtail_audit_trail/pagerecord_detail.html
wagtail_audit_trail/templates/wagtail_audit_trail/pagerecord_list.html
wagtail_audit_trail-1.3.0.dist-info/METADATA
wagtail_audit_trail-1.3.0.dist-info/RECORD
wagtail_audit_trail-1.3.0.dist-info/WHEEL
wagtail_audit_trail-1.3.0.dist-info/top_level.txt
