Metadata-Version: 2.1
Name: wagtail-audit-trail
Version: 1.3.0
Summary: Wagtail audit trail
Home-page: https://github.com/labd/wagtail-audit-trail
Author: Lab Digital
Author-email: opensource@labdigital.nl
License: MIT
Platform: UNKNOWN
Classifier: Development Status :: 3 - Alpha
Classifier: Environment :: Web Environment
Classifier: Framework :: Django
Classifier: Framework :: Django :: 1.11
Classifier: License :: OSI Approved :: MIT License
Classifier: Programming Language :: Python
Classifier: Programming Language :: Python :: 3
Classifier: Programming Language :: Python :: 3.6
Provides-Extra: docs
Provides-Extra: test
Requires-Dist: wagtail (>=2.0)
Provides-Extra: docs
Requires-Dist: sphinx (>=1.4.0); extra == 'docs'
Provides-Extra: test
Requires-Dist: pytest-cov (==2.4.0); extra == 'test'
Requires-Dist: pytest-django (==3.1.2); extra == 'test'
Requires-Dist: pytest (==3.0.5); extra == 'test'
Requires-Dist: requests-mock (==1.1.0); extra == 'test'
Requires-Dist: isort (==4.2.5); extra == 'test'
Requires-Dist: flake8 (==3.0.3); extra == 'test'
Requires-Dist: flake8-blind-except (==0.1.1); extra == 'test'
Requires-Dist: flake8-debugger (==1.4.0); extra == 'test'
Requires-Dist: flake8-imports (==0.1.0); extra == 'test'
